LICENSE
MANIFEST.in
requirements.txt
setup.cfg
setup.py
test_requirements.txt
erc20_limiter/__init__.py
erc20_limiter/index.py
erc20_limiter/limiter.py
erc20_limiter.egg-info/PKG-INFO
erc20_limiter.egg-info/SOURCES.txt
erc20_limiter.egg-info/dependency_links.txt
erc20_limiter.egg-info/requires.txt
erc20_limiter.egg-info/top_level.txt
erc20_limiter/data/Limiter.bin
erc20_limiter/data/Limiter.json
erc20_limiter/data/Limiter.metadata.json
erc20_limiter/data/LimiterIndex.bin
erc20_limiter/data/LimiterIndex.json
erc20_limiter/data/LimiterIndex.metadata.json
erc20_limiter/data/LimiterTokenRegistry.bin
erc20_limiter/data/LimiterTokenRegistry.json
erc20_limiter/data/LimiterTokenRegistry.metadata.json
erc20_limiter/data/__init__.py
erc20_limiter/unittest/__init__.py
erc20_limiter/unittest/base.py
tests/test_base.py
tests/test_index.py